lils/__init__.py
lils/__main__.py
lils/cli.py
lils/commands.py
lils/dbus.py
lils/ink.lark
lils/ink.py
lils/listeners.py
pylils-1.0.0.dist-info/COPYING
pylils-1.0.0.dist-info/METADATA
pylils-1.0.0.dist-info/WHEEL
pylils-1.0.0.dist-info/entry_points.txt
pylils-1.0.0.dist-info/RECORD
