Metadata-Version: 2.1
Name: pylils
Version: 1.0.0
Summary: Linux Immersive Learning System
Author: Daniel Garcia Moreno
Author-email: daniel.garcia@suse.com
Requires-Python: >=3.10,<4.0
Classifier: Programming Language :: Python :: 3
Classifier: Programming Language :: Python :: 3.10
Classifier: Programming Language :: Python :: 3.11
Provides-Extra: dbus
Requires-Dist: lark (>=1.1.5,<2.0.0)
Requires-Dist: pygobject (>=3.42.2,<4.0.0) ; extra == "dbus"
